token_count/__init__.py
tokenpal-0.1.0.dist-info/METADATA
tokenpal-0.1.0.dist-info/WHEEL
tokenpal-0.1.0.dist-info/top_level.txt
tokenpal-0.1.0.dist-info/RECORD
